sitreps_python_api/__init__.py
sitreps_python_api/api_client.py
sitreps_python_api/configuration.py
sitreps_python_api/exceptions.py
sitreps_python_api/model_utils.py
sitreps_python_api/rest.py
sitreps_python_api/api/__init__.py
sitreps_python_api/api/code_coverage_api.py
sitreps_python_api/api/count_line_of_code_api.py
sitreps_python_api/api/default_api.py
sitreps_python_api/api/integration_tests_api.py
sitreps_python_api/api/jira_api.py
sitreps_python_api/api/metadata_api.py
sitreps_python_api/api/project_groups_api.py
sitreps_python_api/api/projects_api.py
sitreps_python_api/api/repositories_api.py
sitreps_python_api/api/sonar_qube_api.py
sitreps_python_api/api/unit_tests_api.py
sitreps_python_api/apis/__init__.py
sitreps_python_api/model/__init__.py
sitreps_python_api/model/cloc_create.py
sitreps_python_api/model/code_coverage_create.py
sitreps_python_api/model/data.py
sitreps_python_api/model/http_validation_error.py
sitreps_python_api/model/integration_test_create.py
sitreps_python_api/model/jira_create.py
sitreps_python_api/model/location_inner.py
sitreps_python_api/model/metadata_create.py
sitreps_python_api/model/project_create.py
sitreps_python_api/model/project_group_create.py
sitreps_python_api/model/project_group_update.py
sitreps_python_api/model/repo_data.py
sitreps_python_api/model/repository_create.py
sitreps_python_api/model/repository_update.py
sitreps_python_api/model/sonar_qube_create.py
sitreps_python_api/model/unit_test_create.py
sitreps_python_api/model/validation_error.py
sitreps_python_api/models/__init__.py
sitreps_python_api-0.0.3.dist-info/METADATA
sitreps_python_api-0.0.3.dist-info/WHEEL
sitreps_python_api-0.0.3.dist-info/licenses/LICENSE
sitreps_python_api-0.0.3.dist-info/RECORD
