Metadata-Version: 2.1
Name: sitreps-python-api
Version: 0.0.3
Summary: Sitreps Python API.
Project-URL: Source, https://github.com/digitronik/sitreps-python-api
Maintainer-email: Nikhil Dhandare <ndhandre@redhat.com>
License-File: LICENSE
Classifier: Development Status :: 4 - Beta
Classifier: Intended Audience :: Developers
Classifier: License :: OSI Approved :: MIT License
Classifier: Operating System :: OS Independent
Classifier: Programming Language :: Python
Classifier: Programming Language :: Python :: 3.8
Classifier: Programming Language :: Python :: 3.9
Classifier: Programming Language :: Python :: 3.10
Classifier: Programming Language :: Python :: Implementation :: CPython
Classifier: Programming Language :: Python :: Implementation :: PyPy
Classifier: Topic :: Software Development :: Testing
Requires-Dist: python-dateutil
Requires-Dist: urllib3>=1.25.3
Provides-Extra: test
Requires-Dist: pre-commit; extra == 'test'
Requires-Dist: pytest; extra == 'test'
Requires-Dist: pytest-cov; extra == 'test'
